hopeit/aws/s3/__init__.py
hopeit/aws/s3/object_storage.py
hopeit/aws/s3/partition.py
hopeit/aws/s3/py.typed
hopeit_aws_s3-0.3.0.dist-info/METADATA
hopeit_aws_s3-0.3.0.dist-info/WHEEL
hopeit_aws_s3-0.3.0.dist-info/top_level.txt
hopeit_aws_s3-0.3.0.dist-info/RECORD
