Metadata-Version: 2.4
Name: hopeit.aws.s3
Version: 0.3.0
Summary: Hopeit Engine S3 Storage Toolkit
Author-email: Leo Smerling & Pablo Canto <contact@hopeit.com.ar>, Leo Smerling <contact@hopeit.com.ar>, Pablo Canto <contact@hopeit.com.ar>
License: Apache 2
Project-URL: Homepage, https://github.com/hopeit-git/hopeit.aws
Project-URL: CI: GitHub Actions, https://github.com/hopeit-git/hopeit.aws/actions?query=workflow
Project-URL: GitHub: issues, https://github.com/hopeit-git/hopeit.aws/issues
Project-URL: GitHub: repo, https://github.com/hopeit-git/hopeit.aws
Classifier: License :: OSI Approved :: Apache Software License
Classifier: Intended Audience :: Developers
Classifier: Programming Language :: Python
Classifier: Programming Language :: Python :: 3.10
Classifier: Programming Language :: Python :: 3.11
Classifier: Programming Language :: Python :: 3.12
Classifier: Programming Language :: Python :: 3.13
Classifier: Development Status :: 5 - Production/Stable
Classifier: Operating System :: POSIX :: Linux
Classifier: Operating System :: MacOS :: MacOS X
Classifier: Operating System :: Microsoft :: Windows
Classifier: Topic :: Internet :: WWW/HTTP
Classifier: Topic :: Software Development :: Libraries :: Python Modules
Classifier: Framework :: AsyncIO
Requires-Dist: hopeit.engine>=0.25.4
Requires-Dist: aioboto3>=14.0.0
